invenio_records/__init__.py
invenio_records/admin.py
invenio_records/api.py
invenio_records/config.py
invenio_records/dictutils.py
invenio_records/errors.py
invenio_records/ext.py
invenio_records/extensions.py
invenio_records/models.py
invenio_records/resolver.py
invenio_records/signals.py
invenio_records/validators.py
invenio_records/alembic/07fb52561c5c_alter_column_from_json_to_jsonb.py
invenio_records/alembic/1095cdf9f350_create_records_branch.py
invenio_records/alembic/428b919be0ea_alter_column_from_json_to_jsonb_for_version.py
invenio_records/alembic/862037093962_create_records_tables.py
invenio_records/data/marc21/authority.xml
invenio_records/data/marc21/bibliographic.xml
invenio_records/dumpers/__init__.py
invenio_records/dumpers/base.py
invenio_records/dumpers/indexedat.py
invenio_records/dumpers/relations.py
invenio_records/dumpers/search.py
invenio_records/systemfields/__init__.py
invenio_records/systemfields/base.py
invenio_records/systemfields/constant.py
invenio_records/systemfields/dict.py
invenio_records/systemfields/model.py
invenio_records/systemfields/relatedmodelfield.py
invenio_records/systemfields/relations/__init__.py
invenio_records/systemfields/relations/errors.py
invenio_records/systemfields/relations/field.py
invenio_records/systemfields/relations/mapping.py
invenio_records/systemfields/relations/modelrelations.py
invenio_records/systemfields/relations/relations.py
invenio_records/systemfields/relations/results.py
invenio_records/translations/messages.pot
invenio_records/translations/ar/LC_MESSAGES/messages.mo
invenio_records/translations/ar/LC_MESSAGES/messages.po
invenio_records/translations/bg/LC_MESSAGES/messages.mo
invenio_records/translations/bg/LC_MESSAGES/messages.po
invenio_records/translations/ca/LC_MESSAGES/messages.mo
invenio_records/translations/ca/LC_MESSAGES/messages.po
invenio_records/translations/cs/LC_MESSAGES/messages.mo
invenio_records/translations/cs/LC_MESSAGES/messages.po
invenio_records-3.1.1.dist-info/licenses/AUTHORS.rst
invenio_records-3.1.1.dist-info/licenses/LICENSE
invenio_records-3.1.1.dist-info/METADATA
invenio_records-3.1.1.dist-info/WHEEL
invenio_records-3.1.1.dist-info/entry_points.txt
invenio_records-3.1.1.dist-info/top_level.txt
invenio_records-3.1.1.dist-info/RECORD
