Metadata-Version: 2.4
Name: invenio-records
Version: 3.1.1
Summary: Invenio-Records is a metadata storage module.
Home-page: https://github.com/inveniosoftware/invenio-records
Author: CERN
Author-email: info@inveniosoftware.org
License: MIT
Keywords: invenio metadata
Platform: any
Classifier: Development Status :: 5 - Production/Stable
Requires-Python: >=3.7
License-File: LICENSE
License-File: AUTHORS.rst
Requires-Dist: arrow>=0.16.0
Requires-Dist: invenio-celery<3.0.0,>=2.0.0
Requires-Dist: invenio-i18n<4.0.0,>=3.0.0
Requires-Dist: jsonpatch>=1.26
Requires-Dist: jsonref>=0.2
Requires-Dist: jsonresolver>=0.3.1
Requires-Dist: jsonschema<5.0.0,>=4.3.0
Provides-Extra: tests
Requires-Dist: pytest-black-ng>=0.4.0; extra == "tests"
Requires-Dist: invenio-admin<2.0.0,>=1.4.0; extra == "tests"
Requires-Dist: pytest-invenio<4.0.0,>=3.0.0; extra == "tests"
Requires-Dist: pytest-mock>=1.6.0; extra == "tests"
Requires-Dist: sphinx>=4.5.0; extra == "tests"
Provides-Extra: admin
Requires-Dist: invenio-admin<2.0.0,>=1.2.1; extra == "admin"
Provides-Extra: mysql
Requires-Dist: invenio-db[mysql,versioning]<3.0.0,>=2.0.0; extra == "mysql"
Provides-Extra: postgresql
Requires-Dist: invenio-db[postgresql,versioning]<3.0.0,>=2.0.0; extra == "postgresql"
Provides-Extra: sqlite
Requires-Dist: invenio-db[versioning]<3.0.0,>=2.0.0; extra == "sqlite"
Provides-Extra: docs
Dynamic: license-file
